{
	"my-2.5": {
		"style": {
			"marginTop": 10,
			"marginBottom": 10
		}
	},
	"mx-5": {
		"style": {
			"marginLeft": 20,
			"marginRight": 20
		}
	},
	"my-2": {
		"style": {
			"marginTop": 8,
			"marginBottom": 8
		}
	},
	"mt-2": {
		"style": {
			"marginTop": 8
		}
	},
	"mr-3": {
		"style": {
			"marginRight": 12
		}
	},
	"hidden": {
		"style": {
			"display": "none"
		}
	},
	"h-10": {
		"style": {
			"height": 40
		}
	},
	"h-8": {
		"style": {
			"height": 32
		}
	},
	"w-10": {
		"style": {
			"width": 40
		}
	},
	"w-full": {
		"style": {
			"width": "100%"
		}
	},
	"flex-1": {
		"style": {
			"flexGrow": 1,
			"flexShrink": 1,
			"flexBasis": "0%"
		}
	},
	"flex-row": {
		"style": {
			"flexDirection": "row"
		}
	},
	"rounded-full": {
		"style": {
			"borderTopLeftRadius": 9999,
			"borderTopRightRadius": 9999,
			"borderBottomRightRadius": 9999,
			"borderBottomLeftRadius": 9999
		}
	},
	"bg-black": {
		"style": {
			"--tw-bg-opacity": 1,
			"backgroundColor": "rgb(0 0 0 / var(--tw-bg-opacity))"
		}
	},
	"p-3": {
		"style": {
			"paddingTop": 12,
			"paddingRight": 12,
			"paddingBottom": 12,
			"paddingLeft": 12
		}
	},
	"px-5": {
		"style": {
			"paddingLeft": 20,
			"paddingRight": 20
		}
	},
	"px-2": {
		"style": {
			"paddingLeft": 8,
			"paddingRight": 8
		}
	},
	"px-1": {
		"style": {
			"paddingLeft": 4,
			"paddingRight": 4
		}
	},
	"py-1": {
		"style": {
			"paddingTop": 4,
			"paddingBottom": 4
		}
	},
	"py-60": {
		"style": {
			"paddingTop": 240,
			"paddingBottom": 240
		}
	},
	"py-6": {
		"style": {
			"paddingTop": 24,
			"paddingBottom": 24
		}
	},
	"py-3": {
		"style": {
			"paddingTop": 12,
			"paddingBottom": 12
		}
	},
	"text-center": {
		"style": {
			"textAlign": "center"
		}
	},
	"text-lg": {
		"style": {
			"fontSize": 18,
			"lineHeight": 28
		}
	},
	"text-sm": {
		"style": {
			"fontSize": 14,
			"lineHeight": 20
		}
	},
	"underline": {
		"style": {
			"textDecorationLine": "underline"
		}
	},
	"line-through": {
		"style": {
			"textDecorationLine": "line-through"
		}
	}
}